pdsim_backend/__init__.py
pdsim_backend/pdsim_unity.py
pdsim_backend-1.0.1.dist-info/LICENCE
pdsim_backend-1.0.1.dist-info/METADATA
pdsim_backend-1.0.1.dist-info/WHEEL
pdsim_backend-1.0.1.dist-info/top_level.txt
pdsim_backend-1.0.1.dist-info/RECORD
