Metadata-Version: 2.2
Name: pdsim-backend
Version: 1.0.1
Summary: Using Unified Planning Library to parse PDDL and generate plans for PDSim.
Author-email: Emanuele De Pellegrin <ed50@hw.ac.uk>, Andy Edmondson <ae2016@hw.ac.uk>
Project-URL: Homepage, https://github.com/Cryoscopic-E/PDSim-Backend
Project-URL: Issues, https://github.com/Cryoscopic-E/PDSim-Backend/issues
Classifier: Programming Language :: Python :: 3
Classifier: Operating System :: OS Independent
Requires-Python: >=3.10
License-File: LICENCE
Requires-Dist: pyzmq~=25.1.1
Requires-Dist: requests~=2.31.0
Requires-Dist: protobuf
Requires-Dist: unified-planning==1.1.0
Requires-Dist: up-fast-downward
Requires-Dist: up-tamer
Requires-Dist: up-pyperplan
